linear_relational/CausalEditor.py
linear_relational/Concept.py
linear_relational/ConceptMatcher.py
linear_relational/Lre.py
linear_relational/Prompt.py
linear_relational/PromptValidator.py
linear_relational/__init__.py
linear_relational/lib/TraceLayer.py
linear_relational/lib/TraceLayerDict.py
linear_relational/lib/balance_grouped_items.py
linear_relational/lib/constants.py
linear_relational/lib/extract_token_activations.py
linear_relational/lib/layer_matching.py
linear_relational/lib/logger.py
linear_relational/lib/token_utils.py
linear_relational/lib/torch_utils.py
linear_relational/lib/util.py
linear_relational/lib/verify_answers_match_expected.py
linear_relational/py.typed
linear_relational/training/Trainer.py
linear_relational/training/train_lre.py
linear_relational-0.6.2.dist-info/LICENSE
linear_relational-0.6.2.dist-info/METADATA
linear_relational-0.6.2.dist-info/WHEEL
linear_relational-0.6.2.dist-info/RECORD
