Metadata-Version: 2.1
Name: linear-relational
Version: 0.6.2
Summary: A Python library for working with Linear Relational Embeddings (LREs) and Linear Relational Concepts (LRCs) for LLMs
Home-page: https://chanind.github.io/linear-relational
Author: David Chanin
Author-email: chanindav@gmail.com
Requires-Python: >=3.10,<4.0
Classifier: Programming Language :: Python :: 3
Classifier: Programming Language :: Python :: 3.10
Classifier: Programming Language :: Python :: 3.11
Classifier: Programming Language :: Python :: 3.12
Requires-Dist: dataclasses-json (>=0.6.2,<0.7.0)
Requires-Dist: tqdm (>=4.0.0)
Requires-Dist: transformers (>=4.42.0,<5.0.0)
Project-URL: Repository, https://github.com/chanind/linear-relational
